{
  "１項": {
    "text": "青色申告書を提出する個人で農業競争力強化支援法（平成二十九年法律第三十五号）第十九条第一項に規定する認定事業再編事業者（同法の施行の日から平成三十三年三月三十一日までの間に同法第十八条第一項の認定を受けた個人に限る。）であるものが、当該認定に係る同法第十八条第一項に規定する事業再編計画（同法第十九条第一項の規定による変更の認定があつたときは、その変更後のもの。以下この項において「認定事業再編計画」という。）に係る同法第十八条第三項第二号の実施期間内において、当該認定事業再編計画に記載された同条第五項に規定する事業再編促進設備等を構成する機械及び装置、建物及びその附属設備並びに構築物（以下この項及び次項において「事業再編促進機械等」という。）でその製作若しくは建設の後事業の用に供されたことのないものを取得し、又は事業再編促進機械等を製作し、若しくは建設して、これを当該個人の事業再編促進対象事業（同法第二条第七項に規定する事業再編促進対象事業をいう。以下この項において同じ。）の用に供した場合（所有権移転外リース取引により取得した当該事業再編促進機械等をその事業再編促進対象事業の用に供した場合を除く。）には、その事業再編促進対象事業の用に供した日（以下この項において「供用日」という。）以後五年以内の日の属する各年分の事業所得の金額の計算上、当該事業再編促進機械等の償却費として必要経費に算入する金額は、供用日以後五年以内（当該認定事業再編計画について同法第十九条第二項又は第三項の規定による認定の取消しがあつた場合には、供用日からその認定の取消しがあつた日までの期間）でその用に供している期間に限り、所得税法第四十九条第一項の規定にかかわらず、当該事業再編促進機械等について同項の規定により計算した償却費の額で当該期間に係るものの百分の百四十（建物及びその附属設備並びに構築物については、百分の百四十五）に相当する金額以下の金額で、当該個人が必要経費として計算した金額とする。ただし、当該事業再編促進機械等の償却費として同項の規定により必要経費に算入される金額を下ることはできない。",
    "gou": []
  },
  "２項": {
    "text": "前条第二項の規定は、前項の規定の適用を受ける事業再編促進機械等の償却費の額を計算する場合について準用する。この場合において、同条第二項中「前項」とあるのは「次条第一項」と、「その合計償却限度額」とあるのは「同項本文の規定により必要経費に算入することができる償却費の限度額」と、「同条第一項」とあるのは「同法第四十九条第一項」と読み替えるものとする。",
    "gou": []
  },
  "３項": {
    "text": "第十一条第三項の規定は、第一項の規定又は前項において準用する前条第二項の規定を適用する場合について準用する。",
    "gou": []
  },
  "４項": {
    "text": "前項に定めるもののほか、第一項及び第二項の規定の適用に関し必要な事項は、政令で定める。",
    "gou": []
  }
}